screpe.py
screpe-0.0.7.data/data/LICENSE
screpe-0.0.7.dist-info/LICENSE
screpe-0.0.7.dist-info/METADATA
screpe-0.0.7.dist-info/WHEEL
screpe-0.0.7.dist-info/top_level.txt
screpe-0.0.7.dist-info/RECORD
