Metadata-Version: 2.1
Name: screpe
Version: 0.0.7
Summary: High-level Python web scraping.
Home-page: https://github.com/shanedrabing/screpe
Author: Shane Drabing
Author-email: shane.drabing@gmail.com
Classifier: Programming Language :: Python :: 3
Classifier: License :: OSI Approved :: MIT License
License-File: LICENSE
Requires-Dist: bs4
Requires-Dist: lxml
Requires-Dist: pandas
Requires-Dist: requests
Requires-Dist: selenium
Requires-Dist: webdriver-manager
